{
  "signals": [
    {
      "ticker": "BRK6",
      "name": "Нефть Brent",
      "group": "commodities",
      "current_price": 104.93,
      "change_pct": -3.72,
      "signal": "HOLD",
      "mode": "BEARISH",
      "score": -1.0,
      "priority": "MEDIUM",
      "stop_loss": 108.0,
      "tp1": 100.33,
      "tp2": 95.72,
      "entry_range": "104.83-105.03",
      "win_rate": 0,
      "reasoning": "Trend: BEARISH. RSI: 64.7. Score: -1.0.",
      "indicators": {
        "rsi": 64.7,
        "ema50": 105.34,
        "ema200": 102.9,
        "bbl": 98.0,
        "bbu": 110.0,
        "macd": 0.8806,
        "macd_signal": -0.0608,
        "atr": 1.53
      },
      "last_update": "21:28"
    },
    {
      "ticker": "SVM6",
      "name": "Серебро",
      "group": "commodities",
      "current_price": 77.59,
      "change_pct": 5.67,
      "signal": "HOLD",
      "mode": "BULLISH",
      "score": 1.0,
      "priority": "MEDIUM",
      "stop_loss": 75.68,
      "tp1": 80.46,
      "tp2": 83.33,
      "entry_range": "77.51-77.67",
      "win_rate": 0,
      "reasoning": "Trend: BULLISH. RSI: 35.1. Score: 1.0.",
      "indicators": {
        "rsi": 35.1,
        "ema50": 75.23,
        "ema200": 76.14,
        "bbl": 73.12,
        "bbu": 79.34,
        "macd": -0.404,
        "macd_signal": 0.1571,
        "atr": 0.96
      },
      "last_update": "21:28"
    },
    {
      "ticker": "MXM6",
      "name": "Индекс МосБиржи",
      "group": "indices",
      "current_price": 276375,
      "change_pct": -2.19,
      "signal": "SHORT",
      "mode": "BEARISH",
      "score": -1.5,
      "priority": "MEDIUM",
      "stop_loss": 277978.76,
      "tp1": 273969.36,
      "tp2": 271563.71,
      "entry_range": "276098.62-276651.37",
      "win_rate": 68.0,
      "reasoning": "Trend: BEARISH. RSI: 43.2. Score: -1.5.",
      "indicators": {
        "rsi": 43.2,
        "ema50": 283635.97,
        "ema200": 287317.11,
        "bbl": 282110.28,
        "bbu": 284272.22,
        "macd": -199.3472,
        "macd_signal": -126.3152,
        "atr": 801.88
      },
      "last_update": "21:28"
    }
  ],
  "all_assets": [
    {
      "ticker": "BRK6",
      "name": "Нефть Brent",
      "group": "commodities",
      "current_price": 104.93,
      "change_pct": -3.72,
      "signal": "HOLD",
      "mode": "BEARISH",
      "score": -1.0,
      "priority": "MEDIUM",
      "stop_loss": 108.0,
      "tp1": 100.33,
      "tp2": 95.72,
      "entry_range": "104.83-105.03",
      "win_rate": 0,
      "reasoning": "Trend: BEARISH. RSI: 64.7. Score: -1.0.",
      "indicators": {
        "rsi": 64.7,
        "ema50": 105.34,
        "ema200": 102.9,
        "bbl": 98.0,
        "bbu": 110.0,
        "macd": 0.8806,
        "macd_signal": -0.0608,
        "atr": 1.53
      },
      "last_update": "21:28"
    },
    {
      "ticker": "NGJ6",
      "name": "Природный газ",
      "group": "commodities",
      "current_price": 2.538,
      "change_pct": -12.99,
      "signal": "HOLD",
      "mode": "BEARISH",
      "score": -0.5,
      "priority": "MEDIUM",
      "stop_loss": null,
      "tp1": null,
      "tp2": null,
      "entry_range": "2.54-2.54",
      "win_rate": 0,
      "reasoning": "Trend: BEARISH. RSI: 49.7. Score: -0.5.",
      "indicators": {
        "rsi": 49.7,
        "ema50": 2.94,
        "ema200": 3.02,
        "bbl": 2.87,
        "bbu": 2.94,
        "macd": -0.0093,
        "macd_signal": -0.0147,
        "atr": 0.02
      },
      "last_update": "21:28"
    },
    {
      "ticker": "GDM6",
      "name": "Золото",
      "group": "commodities",
      "current_price": 4742,
      "change_pct": 1.52,
      "signal": "HOLD",
      "mode": "BULLISH",
      "score": 0.5,
      "priority": "MEDIUM",
      "stop_loss": null,
      "tp1": null,
      "tp2": null,
      "entry_range": "4737.26-4746.74",
      "win_rate": 0,
      "reasoning": "Trend: BULLISH. RSI: 40.1. Score: 0.5.",
      "indicators": {
        "rsi": 40.1,
        "ema50": 4704.03,
        "ema200": 4726.13,
        "bbl": 4658.61,
        "bbu": 4880.78,
        "macd": 0.7891,
        "macd_signal": 22.7603,
        "atr": 38.58
      },
      "last_update": "21:28"
    },
    {
      "ticker": "SVM6",
      "name": "Серебро",
      "group": "commodities",
      "current_price": 77.59,
      "change_pct": 5.67,
      "signal": "HOLD",
      "mode": "BULLISH",
      "score": 1.0,
      "priority": "MEDIUM",
      "stop_loss": 75.68,
      "tp1": 80.46,
      "tp2": 83.33,
      "entry_range": "77.51-77.67",
      "win_rate": 0,
      "reasoning": "Trend: BULLISH. RSI: 35.1. Score: 1.0.",
      "indicators": {
        "rsi": 35.1,
        "ema50": 75.23,
        "ema200": 76.14,
        "bbl": 73.12,
        "bbu": 79.34,
        "macd": -0.404,
        "macd_signal": 0.1571,
        "atr": 0.96
      },
      "last_update": "21:28"
    },
    {
      "ticker": "SiM6",
      "name": "USD/RUB",
      "group": "currency",
      "current_price": 75940,
      "change_pct": -4.44,
      "signal": "HOLD",
      "mode": "BEARISH",
      "score": -0.5,
      "priority": "MEDIUM",
      "stop_loss": null,
      "tp1": null,
      "tp2": null,
      "entry_range": "75864.06-76015.94",
      "win_rate": 0,
      "reasoning": "Trend: BEARISH. RSI: 49.3. Score: -0.5.",
      "indicators": {
        "rsi": 49.3,
        "ema50": 79723.59,
        "ema200": 80602.23,
        "bbl": 79094.12,
        "bbu": 79712.78,
        "macd": -103.7078,
        "macd_signal": -128.8253,
        "atr": 244.44
      },
      "last_update": "21:28"
    },
    {
      "ticker": "MXM6",
      "name": "Индекс МосБиржи",
      "group": "indices",
      "current_price": 276375,
      "change_pct": -2.19,
      "signal": "SHORT",
      "mode": "BEARISH",
      "score": -1.5,
      "priority": "MEDIUM",
      "stop_loss": 277978.76,
      "tp1": 273969.36,
      "tp2": 271563.71,
      "entry_range": "276098.62-276651.37",
      "win_rate": 68.0,
      "reasoning": "Trend: BEARISH. RSI: 43.2. Score: -1.5.",
      "indicators": {
        "rsi": 43.2,
        "ema50": 283635.97,
        "ema200": 287317.11,
        "bbl": 282110.28,
        "bbu": 284272.22,
        "macd": -199.3472,
        "macd_signal": -126.3152,
        "atr": 801.88
      },
      "last_update": "21:28"
    },
    {
      "ticker": "SRM6",
      "name": "Сбербанк",
      "group": "stocks",
      "current_price": 33256,
      "change_pct": 2.23,
      "signal": "HOLD",
      "mode": "BULLISH",
      "score": -0.5,
      "priority": "MEDIUM",
      "stop_loss": null,
      "tp1": null,
      "tp2": null,
      "entry_range": "33222.74-33289.26",
      "win_rate": 0,
      "reasoning": "Trend: BULLISH. RSI: 43.9. Score: -0.5.",
      "indicators": {
        "rsi": 43.9,
        "ema50": 32537.32,
        "ema200": 32593.15,
        "bbl": 32525.47,
        "bbu": 32670.43,
        "macd": 6.8938,
        "macd_signal": 21.962,
        "atr": 66.67
      },
      "last_update": "21:28"
    },
    {
      "ticker": "GZM6",
      "name": "Газпром",
      "group": "stocks",
      "current_price": 12617,
      "change_pct": -9.03,
      "signal": "HOLD",
      "mode": "BEARISH",
      "score": 0.5,
      "priority": "MEDIUM",
      "stop_loss": null,
      "tp1": null,
      "tp2": null,
      "entry_range": "12604.38-12629.62",
      "win_rate": 0,
      "reasoning": "Trend: BEARISH. RSI: 50.9. Score: 0.5.",
      "indicators": {
        "rsi": 50.9,
        "ema50": 13899.22,
        "ema200": 13894.42,
        "bbl": 13758.81,
        "bbu": 13980.69,
        "macd": -15.6413,
        "macd_signal": -17.8113,
        "atr": 60.1
      },
      "last_update": "21:28"
    }
  ],
  "heatmap": [
    {
      "ticker": "BRK6",
      "name": "Нефть Brent",
      "change": -3.72,
      "price": 104.93,
      "signal": "HOLD",
      "mode": "BEARISH",
      "rsi": 64.7
    },
    {
      "ticker": "NGJ6",
      "name": "Природный газ",
      "change": -12.99,
      "price": 2.538,
      "signal": "HOLD",
      "mode": "BEARISH",
      "rsi": 49.7
    },
    {
      "ticker": "GDM6",
      "name": "Золото",
      "change": 1.52,
      "price": 4742,
      "signal": "HOLD",
      "mode": "BULLISH",
      "rsi": 40.1
    },
    {
      "ticker": "SVM6",
      "name": "Серебро",
      "change": 5.67,
      "price": 77.59,
      "signal": "HOLD",
      "mode": "BULLISH",
      "rsi": 35.1
    },
    {
      "ticker": "SiM6",
      "name": "USD/RUB",
      "change": -4.44,
      "price": 75940,
      "signal": "HOLD",
      "mode": "BEARISH",
      "rsi": 49.3
    },
    {
      "ticker": "MXM6",
      "name": "Индекс МосБиржи",
      "change": -2.19,
      "price": 276375,
      "signal": "SHORT",
      "mode": "BEARISH",
      "rsi": 43.2
    },
    {
      "ticker": "SRM6",
      "name": "Сбербанк",
      "change": 2.23,
      "price": 33256,
      "signal": "HOLD",
      "mode": "BULLISH",
      "rsi": 43.9
    },
    {
      "ticker": "GZM6",
      "name": "Газпром",
      "change": -9.03,
      "price": 12617,
      "signal": "HOLD",
      "mode": "BEARISH",
      "rsi": 50.9
    }
  ],
  "market_sentiment": "BEARISH",
  "stats": {
    "total": 8,
    "long": 0,
    "short": 1,
    "hold": 7
  },
  "last_update": "24.04 21:28"
}